CMakeLists.txt
LICENSE
MANIFEST.in
README.md
pyproject.toml
setup.py
include/FlexLexer.h
include/interval.h
include/location.hh
include/position.hh
include/robustness.h
include/signal.h
include/signal_expr.h
include/stack.hh
include/stdafx.h
include/stl_driver.h
include/stl_monitor.h
include/stl_parser.h
include/stl_scanner.h
include/tools.h
include/transducer.h
include/y.tab.h
pybind11/CMakeLists.txt
pybind11/LICENSE
pybind11/include/pybind11/attr.h
pybind11/include/pybind11/buffer_info.h
pybind11/include/pybind11/cast.h
pybind11/include/pybind11/chrono.h
pybind11/include/pybind11/common.h
pybind11/include/pybind11/complex.h
pybind11/include/pybind11/eigen.h
pybind11/include/pybind11/embed.h
pybind11/include/pybind11/eval.h
pybind11/include/pybind11/functional.h
pybind11/include/pybind11/gil.h
pybind11/include/pybind11/iostream.h
pybind11/include/pybind11/numpy.h
pybind11/include/pybind11/operators.h
pybind11/include/pybind11/options.h
pybind11/include/pybind11/pybind11.h
pybind11/include/pybind11/pytypes.h
pybind11/include/pybind11/stl.h
pybind11/include/pybind11/stl_bind.h
pybind11/include/pybind11/detail/class.h
pybind11/include/pybind11/detail/common.h
pybind11/include/pybind11/detail/descr.h
pybind11/include/pybind11/detail/init.h
pybind11/include/pybind11/detail/internals.h
pybind11/include/pybind11/detail/type_caster_base.h
pybind11/include/pybind11/detail/typeid.h
pybind11/include/pybind11/stl/filesystem.h
pybind11/tests/CMakeLists.txt
pybind11/tests/test_cmake_build/CMakeLists.txt
pybind11/tests/test_cmake_build/installed_embed/CMakeLists.txt
pybind11/tests/test_cmake_build/installed_function/CMakeLists.txt
pybind11/tests/test_cmake_build/installed_target/CMakeLists.txt
pybind11/tests/test_cmake_build/subdirectory_embed/CMakeLists.txt
pybind11/tests/test_cmake_build/subdirectory_function/CMakeLists.txt
pybind11/tests/test_cmake_build/subdirectory_target/CMakeLists.txt
pybind11/tests/test_embed/CMakeLists.txt
pybind11/tools/FindCatch.cmake
stlrom.egg-info/PKG-INFO
stlrom.egg-info/SOURCES.txt
stlrom.egg-info/dependency_links.txt
stlrom.egg-info/top_level.txt
