Metadata-Version: 2.1
Name: stlrom
Version: 0.2.2
Summary: A library for robust online monitoring of STL specifications.
Home-page: https://github.com/decyphir/STLRom
Author: Alexandre Donzé
Author-email: alex@decyphir.com
Classifier: License :: OSI Approved :: BSD License
Classifier: Programming Language :: Python :: 3
Classifier: Programming Language :: C++
Classifier: Development Status :: 3 - Alpha
Requires-Python: >=3.10
License-File: LICENSE
